[{"id":1,"price":["720","50","30","40","120","120","80","50","25","200","120","251","300","200","50","30","600","80","630","200","40","40","30","60","50","150","20","30"],"stock":["Chicken","Lemon","Salt","Yogurt","Onions","Garlic","Ginger","Pepper","Coriander","Garam Masala","Vegetable Oil","Basmati Rice","Cumin","Chilli Powder","Tomatoes","Mint Leaves","Cardamon","Cinnamon stick","Fish","Mustard","Sugar","Beans","Carrots","Bell peppers","Vinegar","Soy sauce","Cabbage","Spring Onion"],"stockQty":["4800","400","1000","100","5000","1000","1000","1000","500","1000","1000","5000","1000","1000","2000","100","1000","1000","2100","1000","1000","1000","1000","1000","1000","1000","1000","100"],"exp":[null,null,null,"2024-07-06",null,null,null,null,null,null,null,null,null,null,null,null,null,null,null,null,null,null,null,null,null,null,null,null],"sup":"2024-06-29"},{"id":2,"price":["720","50","30","40","120","120","80","50","25","200","120","251","300","200","50","30","600","80","630","200","40","40","30","60","50","150","20","30","50","50","200"],"stock":["Chicken","Lemon","Salt","Yogurt","Onions","Garlic","Ginger","Pepper","Coriander","Garam Masala","Vegetable Oil","Basmati Rice","Cumin","Chilli Powder","Tomatoes","Mint Leaves","Cardamon","Cinnamon stick","Fish","Mustard","Sugar","Beans","Carrots","Bell peppers","Vinegar","Soy sauce","Cabbage","Spring Onion","Paneer","Cabbage","Chilli Sauce"],"stockQty":["4800","400","1000","100","5000","1000","1000","1000","500","1000","1000","5000","1000","1000","2000","100","1000","1000","2100","1000","1000","1000","1000","1000","1000","1000","1000","100","1000","2000","1000"],"exp":[null,null,null,"2024-07-06",null,null,null,null,null,null,null,null,null,null,null,null,null,null,null,null,null,null,null,null,null,null,null,null,"2024-07-06",null,null],"sup":"2024-06-29"},{"id":3,"price":["101"],"stock":["Basmati Rice"],"stockQty":["2000"],"exp":[null],"sup":"2024-06-30"},{"id":4,"price":["101","450"],"stock":["Basmati Rice","Mutton"],"stockQty":["2000","5000"],"exp":[null,null],"sup":"2024-06-30"}]